<?xml version="1.0" encoding="utf-8" ?>
<dwsync>
<file name="index.htm" server="zakhar0o.beget.tech/shevkunenko.ru/public_html/" local="132794956091671987" remote="132494292000000000" Dst="0" />
<file name="jukov-odessa-ad.htm" server="zakhar0o.beget.tech/shevkunenko.ru/public_html/" local="132794956091841536" remote="132494292000000000" Dst="0" />
<file name="jukov-odessa-ml.htm" server="zakhar0o.beget.tech/shevkunenko.ru/public_html/" local="132794956092050972" remote="132494292000000000" Dst="0" />
<file name="jukov-odessa-ok.htm" server="zakhar0o.beget.tech/shevkunenko.ru/public_html/" local="132794956092556683" remote="132494292000000000" Dst="0" />
<file name="jukov-odessa-vk.htm" server="zakhar0o.beget.tech/shevkunenko.ru/public_html/" local="132794956092746172" remote="132494292000000000" Dst="0" />
<file name="jukov-odessa.htm" server="zakhar0o.beget.tech/shevkunenko.ru/public_html/" local="132794956093095262" remote="132494292000000000" Dst="0" />
<file name="likvidaciya1-ad.htm" server="zakhar0o.beget.tech/shevkunenko.ru/public_html/" local="132794956093254827" remote="132494292000000000" Dst="0" />
<file name="likvidaciya1-ml.htm" server="zakhar0o.beget.tech/shevkunenko.ru/public_html/" local="132794956093524104" remote="132494292000000000" Dst="0" />
<file name="likvidaciya1-ok.htm" server="zakhar0o.beget.tech/shevkunenko.ru/public_html/" local="132794956093803349" remote="132494292000000000" Dst="0" />
<file name="likvidaciya1-vk.htm" server="zakhar0o.beget.tech/shevkunenko.ru/public_html/" local="132794956093913057" remote="132494292000000000" Dst="0" />
<file name="likvidaciya1.htm" server="zakhar0o.beget.tech/shevkunenko.ru/public_html/" local="132794956094441647" remote="132494292000000000" Dst="0" />
<file name="likvidaciya10-ml.htm" server="zakhar0o.beget.tech/shevkunenko.ru/public_html/" local="132794956094551352" remote="132494292000000000" Dst="0" />
<file name="likvidaciya10-ad.htm" server="zakhar0o.beget.tech/shevkunenko.ru/public_html/" local="132794956094571298" remote="132494292000000000" Dst="0" />
<file name="likvidaciya10-vk.htm" server="zakhar0o.beget.tech/shevkunenko.ru/public_html/" local="132794956095190892" remote="132494292000000000" Dst="0" />
<file name="likvidaciya10-ok.htm" server="zakhar0o.beget.tech/shevkunenko.ru/public_html/" local="132794956095470149" remote="132494292000000000" Dst="0" />
<file name="likvidaciya10.htm" server="zakhar0o.beget.tech/shevkunenko.ru/public_html/" local="132794956095480135" remote="132494292000000000" Dst="0" />
<file name="likvidaciya11-ad.htm" server="zakhar0o.beget.tech/shevkunenko.ru/public_html/" local="132794956095968822" remote="132494292000000000" Dst="0" />
<file name="likvidaciya11-ok.htm" server="zakhar0o.beget.tech/shevkunenko.ru/public_html/" local="132794956096198197" remote="132494292000000000" Dst="0" />
<file name="likvidaciya11-ml.htm" server="zakhar0o.beget.tech/shevkunenko.ru/public_html/" local="132794956096228124" remote="132494292000000000" Dst="0" />
<file name="likvidaciya11-vk.htm" server="zakhar0o.beget.tech/shevkunenko.ru/public_html/" local="132794956096547271" remote="132494292000000000" Dst="0" />
<file name="likvidaciya11.htm" server="zakhar0o.beget.tech/shevkunenko.ru/public_html/" local="132794956096846474" remote="132494292000000000" Dst="0" />
<file name="likvidaciya12-ad.htm" server="zakhar0o.beget.tech/shevkunenko.ru/public_html/" local="132794956097185567" remote="132494292000000000" Dst="0" />
<file name="likvidaciya12-ml.htm" server="zakhar0o.beget.tech/shevkunenko.ru/public_html/" local="132794956097285297" remote="132494292000000000" Dst="0" />
<file name="likvidaciya12-ok.htm" server="zakhar0o.beget.tech/shevkunenko.ru/public_html/" local="132794956097544614" remote="132494292000000000" Dst="0" />
<file name="likvidaciya12-vk.htm" server="zakhar0o.beget.tech/shevkunenko.ru/public_html/" local="132794956098023330" remote="132494292000000000" Dst="0" />
<file name="likvidaciya12.htm" server="zakhar0o.beget.tech/shevkunenko.ru/public_html/" local="132794956098093131" remote="132494292000000000" Dst="0" />
<file name="likvidaciya13-ad.htm" server="zakhar0o.beget.tech/shevkunenko.ru/public_html/" local="132794956098182903" remote="132494292000000000" Dst="0" />
<file name="likvidaciya13-ml.htm" server="zakhar0o.beget.tech/shevkunenko.ru/public_html/" local="132794956098681559" remote="132494292000000000" Dst="0" />
<file name="likvidaciya13-ok.htm" server="zakhar0o.beget.tech/shevkunenko.ru/public_html/" local="132794956098721466" remote="132494292000000000" Dst="0" />
<file name="likvidaciya13-vk.htm" server="zakhar0o.beget.tech/shevkunenko.ru/public_html/" local="132794956098930901" remote="132494292000000000" Dst="0" />
<file name="likvidaciya14-ad.htm" server="zakhar0o.beget.tech/shevkunenko.ru/public_html/" local="132794956099429568" remote="132494292000000000" Dst="0" />
<file name="likvidaciya13.htm" server="zakhar0o.beget.tech/shevkunenko.ru/public_html/" local="132794956099519328" remote="132494292000000000" Dst="0" />
<file name="likvidaciya14-ml.htm" server="zakhar0o.beget.tech/shevkunenko.ru/public_html/" local="132794956099648971" remote="132494292000000000" Dst="0" />
<file name="likvidaciya14-ok.htm" server="zakhar0o.beget.tech/shevkunenko.ru/public_html/" local="132794956100167589" remote="132494292000000000" Dst="0" />
<file name="likvidaciya14-vk.htm" server="zakhar0o.beget.tech/shevkunenko.ru/public_html/" local="132794956100337137" remote="132494292000000000" Dst="0" />
<file name="likvidaciya14.htm" server="zakhar0o.beget.tech/shevkunenko.ru/public_html/" local="132794956100367054" remote="132494292000000000" Dst="0" />
<file name="likvidaciya2-ad.htm" server="zakhar0o.beget.tech/shevkunenko.ru/public_html/" local="132794956100897217" remote="132494292000000000" Dst="0" />
<file name="likvidaciya2-ml.htm" server="zakhar0o.beget.tech/shevkunenko.ru/public_html/" local="132794956100987000" remote="132494292000000000" Dst="0" />
<file name="likvidaciya2-ok.htm" server="zakhar0o.beget.tech/shevkunenko.ru/public_html/" local="132794956101055615" remote="132494292000000000" Dst="0" />
<file name="likvidaciya2-vk.htm" server="zakhar0o.beget.tech/shevkunenko.ru/public_html/" local="132794956101502411" remote="132494292000000000" Dst="0" />
<file name="likvidaciya2.htm" server="zakhar0o.beget.tech/shevkunenko.ru/public_html/" local="132794956101751747" remote="132494292000000000" Dst="0" />
<file name="likvidaciya3-ad.htm" server="zakhar0o.beget.tech/shevkunenko.ru/public_html/" local="132794956101761721" remote="132494292000000000" Dst="0" />
<file name="likvidaciya3-ml.htm" server="zakhar0o.beget.tech/shevkunenko.ru/public_html/" local="132794956102230466" remote="132494292000000000" Dst="0" />
<file name="likvidaciya3-ok.htm" server="zakhar0o.beget.tech/shevkunenko.ru/public_html/" local="132794956102360120" remote="132494292000000000" Dst="0" />
<file name="likvidaciya3-vk.htm" server="zakhar0o.beget.tech/shevkunenko.ru/public_html/" local="132794956102370095" remote="132494292000000000" Dst="0" />
<file name="likvidaciya3.htm" server="zakhar0o.beget.tech/shevkunenko.ru/public_html/" local="132794956103148006" remote="132494292000000000" Dst="0" />
<file name="likvidaciya4-ml.htm" server="zakhar0o.beget.tech/shevkunenko.ru/public_html/" local="132794956103287637" remote="132494292000000000" Dst="0" />
<file name="likvidaciya4-ad.htm" server="zakhar0o.beget.tech/shevkunenko.ru/public_html/" local="132794956103387371" remote="132494292000000000" Dst="0" />
<file name="likvidaciya4-vk.htm" server="zakhar0o.beget.tech/shevkunenko.ru/public_html/" local="132794956104005720" remote="132494292000000000" Dst="0" />
<file name="likvidaciya4-ok.htm" server="zakhar0o.beget.tech/shevkunenko.ru/public_html/" local="132794956104025670" remote="132494292000000000" Dst="0" />
<file name="likvidaciya4.htm" server="zakhar0o.beget.tech/shevkunenko.ru/public_html/" local="132794956104205183" remote="132494292000000000" Dst="0" />
<file name="likvidaciya5-ml.htm" server="zakhar0o.beget.tech/shevkunenko.ru/public_html/" local="132794956104803596" remote="132494292000000000" Dst="0" />
<file name="likvidaciya5-ad.htm" server="zakhar0o.beget.tech/shevkunenko.ru/public_html/" local="132794956104823534" remote="132494292000000000" Dst="0" />
<file name="likvidaciya5-ok.htm" server="zakhar0o.beget.tech/shevkunenko.ru/public_html/" local="132794956105042945" remote="132494292000000000" Dst="0" />
<file name="likvidaciya5-vk.htm" server="zakhar0o.beget.tech/shevkunenko.ru/public_html/" local="132794956105641348" remote="132494292000000000" Dst="0" />
<file name="likvidaciya5.htm" server="zakhar0o.beget.tech/shevkunenko.ru/public_html/" local="132794956105661298" remote="132494292000000000" Dst="0" />
<file name="likvidaciya6-ad.htm" server="zakhar0o.beget.tech/shevkunenko.ru/public_html/" local="132794956105980439" remote="132494292000000000" Dst="0" />
<file name="likvidaciya6-ml.htm" server="zakhar0o.beget.tech/shevkunenko.ru/public_html/" local="132794956106219798" remote="132494292000000000" Dst="0" />
<file name="likvidaciya6-ok.htm" server="zakhar0o.beget.tech/shevkunenko.ru/public_html/" local="132794956106289608" remote="132494292000000000" Dst="0" />
<file name="likvidaciya6-vk.htm" server="zakhar0o.beget.tech/shevkunenko.ru/public_html/" local="132794956106738416" remote="132494292000000000" Dst="0" />
<file name="likvidaciya7-ad.htm" server="zakhar0o.beget.tech/shevkunenko.ru/public_html/" local="132794956106888017" remote="132494292000000000" Dst="0" />
<file name="likvidaciya6.htm" server="zakhar0o.beget.tech/shevkunenko.ru/public_html/" local="132794956106907961" remote="132494292000000000" Dst="0" />
<file name="likvidaciya7-ml.htm" server="zakhar0o.beget.tech/shevkunenko.ru/public_html/" local="132794956107526298" remote="132494292000000000" Dst="0" />
<file name="likvidaciya7-ok.htm" server="zakhar0o.beget.tech/shevkunenko.ru/public_html/" local="132794956107685882" remote="132494292000000000" Dst="0" />
<file name="likvidaciya7-vk.htm" server="zakhar0o.beget.tech/shevkunenko.ru/public_html/" local="132794956107705820" remote="132494292000000000" Dst="0" />
<file name="likvidaciya7.htm" server="zakhar0o.beget.tech/shevkunenko.ru/public_html/" local="132794956108274304" remote="132494292000000000" Dst="0" />
<file name="likvidaciya8-ad.htm" server="zakhar0o.beget.tech/shevkunenko.ru/public_html/" local="132794956108364070" remote="132494292000000000" Dst="0" />
<file name="likvidaciya8-ml.htm" server="zakhar0o.beget.tech/shevkunenko.ru/public_html/" local="132794956108423904" remote="132494292000000000" Dst="0" />
<file name="likvidaciya8-vk.htm" server="zakhar0o.beget.tech/shevkunenko.ru/public_html/" local="132794956108932536" remote="132494292000000000" Dst="0" />
<file name="likvidaciya8-ok.htm" server="zakhar0o.beget.tech/shevkunenko.ru/public_html/" local="132794956109102090" remote="132494292000000000" Dst="0" />
<file name="likvidaciya8.htm" server="zakhar0o.beget.tech/shevkunenko.ru/public_html/" local="132794956109161928" remote="132494292000000000" Dst="0" />
<file name="likvidaciya9-ad.htm" server="zakhar0o.beget.tech/shevkunenko.ru/public_html/" local="132794956109690527" remote="132494292000000000" Dst="0" />
<file name="likvidaciya9-ok.htm" server="zakhar0o.beget.tech/shevkunenko.ru/public_html/" local="132794956109850100" remote="132494292000000000" Dst="0" />
<file name="likvidaciya9-ml.htm" server="zakhar0o.beget.tech/shevkunenko.ru/public_html/" local="132794956110049568" remote="132494292000000000" Dst="0" />
<file name="likvidaciya9-vk.htm" server="zakhar0o.beget.tech/shevkunenko.ru/public_html/" local="132794956110438513" remote="132494292000000000" Dst="0" />
<file name="likvidaciya9.htm" server="zakhar0o.beget.tech/shevkunenko.ru/public_html/" local="132794956110518310" remote="132494292000000000" Dst="0" />
</dwsync>