<?xml version="1.0" encoding="utf-8" ?>
<dwsync>
<file name="da-audio.png" server="zakhar0o.beget.tech/shevkunenko.ru/public_html/" local="132433812000000000" remote="132433812000000000" Dst="0" />
<file name="da-audio2.png" server="zakhar0o.beget.tech/shevkunenko.ru/public_html/" local="132362100000000000" remote="132362100000000000" Dst="0" />
<file name="da.png" server="zakhar0o.beget.tech/shevkunenko.ru/public_html/" local="132433812000000000" remote="132433812000000000" Dst="0" />
<file name="da1.png" server="zakhar0o.beget.tech/shevkunenko.ru/public_html/" local="131963796000000000" remote="131963796000000000" Dst="0" />
<file name="da10.png" server="zakhar0o.beget.tech/shevkunenko.ru/public_html/" local="131963796000000000" remote="131963796000000000" Dst="0" />
<file name="da10300.png" server="zakhar0o.beget.tech/shevkunenko.ru/public_html/" local="131963796000000000" remote="131963796000000000" Dst="0" />
<file name="da11.png" server="zakhar0o.beget.tech/shevkunenko.ru/public_html/" local="132433812000000000" remote="132433812000000000" Dst="0" />
<file name="da11300.png" server="zakhar0o.beget.tech/shevkunenko.ru/public_html/" local="132433812000000000" remote="132433812000000000" Dst="0" />
<file name="da12.png" server="zakhar0o.beget.tech/shevkunenko.ru/public_html/" local="132433812000000000" remote="132433812000000000" Dst="0" />
<file name="da12300.png" server="zakhar0o.beget.tech/shevkunenko.ru/public_html/" local="132433812000000000" remote="132433812000000000" Dst="0" />
<file name="da13.png" server="zakhar0o.beget.tech/shevkunenko.ru/public_html/" local="132433812000000000" remote="132433812000000000" Dst="0" />
<file name="da1300.png" server="zakhar0o.beget.tech/shevkunenko.ru/public_html/" local="131963796000000000" remote="131963796000000000" Dst="0" />
<file name="da13300.png" server="zakhar0o.beget.tech/shevkunenko.ru/public_html/" local="132433812000000000" remote="132433812000000000" Dst="0" />
<file name="da14.png" server="zakhar0o.beget.tech/shevkunenko.ru/public_html/" local="132433812000000000" remote="132433812000000000" Dst="0" />
<file name="da14300.png" server="zakhar0o.beget.tech/shevkunenko.ru/public_html/" local="132433812000000000" remote="132433812000000000" Dst="0" />
<file name="da15.png" server="zakhar0o.beget.tech/shevkunenko.ru/public_html/" local="132433812000000000" remote="132433812000000000" Dst="0" />
<file name="da15300.png" server="zakhar0o.beget.tech/shevkunenko.ru/public_html/" local="132433812000000000" remote="132433812000000000" Dst="0" />
<file name="da16.png" server="zakhar0o.beget.tech/shevkunenko.ru/public_html/" local="132433812000000000" remote="132433812000000000" Dst="0" />
<file name="da16300.png" server="zakhar0o.beget.tech/shevkunenko.ru/public_html/" local="132433812000000000" remote="132433812000000000" Dst="0" />
<file name="da2.png" server="zakhar0o.beget.tech/shevkunenko.ru/public_html/" local="131963796000000000" remote="131963796000000000" Dst="0" />
<file name="da2300.png" server="zakhar0o.beget.tech/shevkunenko.ru/public_html/" local="131963796000000000" remote="131963796000000000" Dst="0" />
<file name="da3.png" server="zakhar0o.beget.tech/shevkunenko.ru/public_html/" local="131963796000000000" remote="131963796000000000" Dst="0" />
<file name="da300.png" server="zakhar0o.beget.tech/shevkunenko.ru/public_html/" local="132433812000000000" remote="132433812000000000" Dst="0" />
<file name="da3300.png" server="zakhar0o.beget.tech/shevkunenko.ru/public_html/" local="131963796000000000" remote="131963796000000000" Dst="0" />
<file name="da4.png" server="zakhar0o.beget.tech/shevkunenko.ru/public_html/" local="131963796000000000" remote="131963796000000000" Dst="0" />
<file name="da4300.png" server="zakhar0o.beget.tech/shevkunenko.ru/public_html/" local="131963796000000000" remote="131963796000000000" Dst="0" />
<file name="da5.png" server="zakhar0o.beget.tech/shevkunenko.ru/public_html/" local="131963796000000000" remote="131963796000000000" Dst="0" />
<file name="da5300.png" server="zakhar0o.beget.tech/shevkunenko.ru/public_html/" local="131963796000000000" remote="131963796000000000" Dst="0" />
<file name="da6.png" server="zakhar0o.beget.tech/shevkunenko.ru/public_html/" local="131963796000000000" remote="131963796000000000" Dst="0" />
<file name="da6300.png" server="zakhar0o.beget.tech/shevkunenko.ru/public_html/" local="131963796000000000" remote="131963796000000000" Dst="0" />
<file name="da7.png" server="zakhar0o.beget.tech/shevkunenko.ru/public_html/" local="131963796000000000" remote="131963796000000000" Dst="0" />
<file name="da7300.png" server="zakhar0o.beget.tech/shevkunenko.ru/public_html/" local="131963796000000000" remote="131963796000000000" Dst="0" />
<file name="da8.png" server="zakhar0o.beget.tech/shevkunenko.ru/public_html/" local="131963796000000000" remote="131963796000000000" Dst="0" />
<file name="da8300.png" server="zakhar0o.beget.tech/shevkunenko.ru/public_html/" local="131963796000000000" remote="131963796000000000" Dst="0" />
<file name="da9.png" server="zakhar0o.beget.tech/shevkunenko.ru/public_html/" local="131963796000000000" remote="131963796000000000" Dst="0" />
<file name="da9300.png" server="zakhar0o.beget.tech/shevkunenko.ru/public_html/" local="131963796000000000" remote="131963796000000000" Dst="0" />
<file name="dabook1-156.png" server="zakhar0o.beget.tech/shevkunenko.ru/public_html/" local="132433812000000000" remote="132433812000000000" Dst="0" />
<file name="dabook1.png" server="zakhar0o.beget.tech/shevkunenko.ru/public_html/" local="132432084000000000" remote="132432084000000000" Dst="0" />
<file name="dabook2-156.png" server="zakhar0o.beget.tech/shevkunenko.ru/public_html/" local="132362100000000000" remote="132362100000000000" Dst="0" />
<file name="dabook2.png" server="zakhar0o.beget.tech/shevkunenko.ru/public_html/" local="132432084000000000" remote="132432084000000000" Dst="0" />
<file name="dabook3-156.png" server="zakhar0o.beget.tech/shevkunenko.ru/public_html/" local="132362100000000000" remote="132362100000000000" Dst="0" />
<file name="dabook3.png" server="zakhar0o.beget.tech/shevkunenko.ru/public_html/" local="132432084000000000" remote="132432084000000000" Dst="0" />
<file name="strah-audio.png" server="zakhar0o.beget.tech/shevkunenko.ru/public_html/" local="132362100000000000" remote="132362100000000000" Dst="0" />
<file name="strah2-audio.png" server="zakhar0o.beget.tech/shevkunenko.ru/public_html/" local="132362100000000000" remote="132362100000000000" Dst="0" />
</dwsync>